{
  "$schema": "https://ui.shadcn.com/schema/registry-item.json",
  "name": "threads-logo",
  "type": "registry:ui",
  "title": "Threads Logo",
  "description": "Threads logo component with brand and grayscale color schemes",
  "registryDependencies": [],
  "dependencies": [],
  "files": [
    {
      "path": "registry/default/blocks/logos/threads-logo/components/logos/threads.tsx",
      "type": "registry:component"
    }
  ],
  "docs": "Threads logo with 2 color schemes (brand black, grayscale). Grayscale uses currentColor for theme-awareness.",
  "categories": ["Social", "logo", "brand"],
  "meta": {
    "hasVariants": true,
    "variants": ["icon-brand", "icon-grayscale"],
    "variantTypes": {
      "colorSchemes": ["brand", "grayscale"]
    }
  }
}
