{
  "$schema": "https://ui.shadcn.com/schema/registry-item.json",
  "name": "suno-logo",
  "type": "registry:ui",
  "title": "Suno Logo",
  "description": "Suno logo with variant support",
  "registryDependencies": [],
  "dependencies": [],
  "categories": ["AI", "Media", "logo", "brand"],
  "meta": {
    "hasVariants": true,
    "variants": ["icon", "wordmark"],
    "variantTypes": {
      "base": ["icon", "wordmark"],
      "modes": ["dark", "light"]
    }
  },
  "files": [
    {
      "path": "registry/default/blocks/logos/suno-logo/components/logos/suno.tsx",
      "type": "registry:component"
    }
  ],
  "docs": "Suno logo with 2 base variant(s) (icon, wordmark) and 2 modes (dark, light) = 4 total combinations."
}
